styled/__init__.py
styled/__main__.py
styled/assets.py
styled/styled.py
styled/tests.py
styled-0.3.1.dist-info/LICENSE
styled-0.3.1.dist-info/METADATA
styled-0.3.1.dist-info/WHEEL
styled-0.3.1.dist-info/entry_points.txt
styled-0.3.1.dist-info/top_level.txt
styled-0.3.1.dist-info/RECORD
